connectsquare/__init__.py
connectsquare/connect_square.css
connectsquare/connect_square.py
connectsquare-1.0.0.dist-info/METADATA
connectsquare-1.0.0.dist-info/WHEEL
connectsquare-1.0.0.dist-info/entry_points.txt
connectsquare-1.0.0.dist-info/licenses/LICENSE
connectsquare-1.0.0.dist-info/RECORD
